{
  "kind": "singleType",
  "collectionName": "stores",
  "info": {
    "singularName": "store",
    "pluralName": "stores",
    "displayName": "Store",
    "description": ""
  },
  "options": {
    "draftAndPublish": true
  },
  "pluginOptions": {},
  "attributes": {
    "name": {
      "type": "string"
    },
    "banner": {
      "type": "media",
      "multiple": false,
      "required": false,
      "allowedTypes": [
        "videos",
        "images"
      ]
    },
    "description": {
      "type": "text"
    },
    "content": {
      "type": "richtext"
    },
    "promos": {
      "displayName": "Promotions",
      "type": "component",
      "repeatable": false,
      "component": "frontend.promotions"
    }
  }
}
